<mets:METS xmlns:mets="http://www.loc.gov/METS/" xmlns:xlink="http://www.w3.org/TR/xlink/" xmlns:xsi="http://www.w3.org/2001/XMLSchema-instance" xmlns:dim="http://www.dspace.org/xmlns/dspace/dim" PROFILE="DSPACE METS SIP Profile 1.0" LABEL="DSpace Item" OBJID="/handle/2027.42/93229" ID="hdl:2027.42/93229" OBJEDIT="/admin/item?itemID=94570">
<mets:dmdSec GROUPID="group_dmd_0" ID="dmd_1">
<mets:mdWrap OTHERMDTYPE="DIM" MDTYPE="OTHER">
<mets:xmlData>
<dim:dim dspaceType="ITEM">
<dim:field qualifier="author" mdschema="dc" language="en_US" element="contributor">Michigan Public Media. University of Michigan</dim:field>
<dim:field qualifier="other" mdschema="dc" language="en_US" element="contributor">Noori, Margaret</dim:field>
<dim:field qualifier="other" mdschema="dc" language="en_US" element="contributor">Kimewon, Howard</dim:field>
<dim:field qualifier="other" mdschema="dc" language="en_US" element="contributor">Quinn, Robert</dim:field>
<dim:field qualifier="other" mdschema="dc" language="en_US" element="contributor">Spreitzer, Gretchen</dim:field>
<dim:field qualifier="other" mdschema="dc" language="en_US" element="contributor">Wooten, Lynn</dim:field>
<dim:field qualifier="other" mdschema="dc" language="en_US" element="contributor">Brown, Susan</dim:field>
<dim:field qualifier="other" mdschema="dc" language="en_US" element="contributor">Hurvitz, Edward</dim:field>
<dim:field qualifier="temporal" mdschema="dc" language="en_US" element="coverage">2010-2011</dim:field>
<dim:field qualifier="accessioned" mdschema="dc" element="date">2012-08-30T20:00:36Z</dim:field>
<dim:field qualifier="available" mdschema="dc" element="date">2012-08-30T20:00:36Z</dim:field>
<dim:field qualifier="created" mdschema="dc" language="en_US" element="date">2011</dim:field>
<dim:field qualifier="issued" mdschema="dc" language="en_US" element="date">2012</dim:field>
<dim:field qualifier="other" mdschema="dc" language="en_US" element="identifier">2012091_0003</dim:field>
<dim:field qualifier="uri" mdschema="dc" element="identifier">http://hdl.handle.net/2027.42/93229</dim:field>
<dim:field qualifier="abstract" mdschema="dc" language="en_US" element="description">Feature 1 - Facing the possible extinction of spoken Ojibwe, Lecturers in the Native American Studies Program are engaging students in the preservation of the language and community members in the revitalization of the culture. Feature 2 - A group of faculty at the U-M Ross School of Business lead MBA students and business leaders through an examination of organizational excellence,with an eye toward achieving transformational change.  Feature 3 - Many Stroke victims and adults with Cerebral Palsy have limited access to physical and occupational therapy. Project ULTrA (Upper Limb Training in Adults with Hemiplegic Cerebral Palsy) now provides home based programs for patients to engage in therapy under the watchful eye of U-M based trainers</dim:field>
<dim:field mdschema="dc" language="en_US" element="rights">Copyright is held by the Board of Regents, University of Michigan.</dim:field>
<dim:field mdschema="dc" language="en_US" element="title">"Out of the Blue" Season 3 Episode 02</dim:field>
<dim:field mdschema="dc" language="en_US" element="type">Video</dim:field>
<dim:field qualifier="affiliationum" mdschema="dc" language="en_US" element="contributor">Margaret Noori (Lecturer, Native American Studies)</dim:field>
<dim:field qualifier="affiliationum" mdschema="dc" language="en_US" element="contributor">Howard Kimewon (Lecturer, Native American Studies)</dim:field>
<dim:field qualifier="affiliationum" mdschema="dc" language="en_US" element="contributor">Robert Quinn (Professor, Ross School of Business)</dim:field>
<dim:field qualifier="affiliationum" mdschema="dc" language="en_US" element="contributor">Gretchen Spreitzer (Professor, Ross School of Business)</dim:field>
<dim:field qualifier="affiliationum" mdschema="dc" language="en_US" element="contributor">Lynn Wooten (Assoc. Professor, Ross School of Business)</dim:field>
<dim:field qualifier="affiliationum" mdschema="dc" language="en_US" element="contributor">Dr. Susan Brown (Professor, Kinesiology)</dim:field>
<dim:field qualifier="affiliationum" mdschema="dc" language="en_US" element="contributor">Dr. Edward Hurvitz (Professor, UMHS)</dim:field>
<dim:field qualifier="bitstreamurl" mdschema="dc" element="description">http://deepblue.lib.umich.edu/bitstream/2027.42/93229/1/OOTB_302_PBS_build.mov</dim:field>
<dim:field qualifier="md5checksum" mdschema="dc" language="en_US" element="description">57f0e3237f6d24bc4f95c5cd5eee79dc</dim:field>
<dim:field qualifier="access" mdschema="dc" language="en_US" element="rights">The collection is open for research</dim:field>
<dim:field mdschema="dc" element="owningcollname">Out of the Blue: The Michigan Difference (television program)</dim:field>
</dim:dim>
</mets:xmlData>
</mets:mdWrap>
</mets:dmdSec>
<mets:fileSec>
<mets:fileGrp USE="CONTENT">
<mets:file GROUPID="group_file_323082" CHECKSUM="57f0e3237f6d24bc4f95c5cd5eee79dc" MIMETYPE="video/quicktime" SIZE="3431442521" ID="file_323082" CHECKSUMTYPE="MD5">
<mets:FLocat LOCTYPE="URL" xlink:label="Includes: the Native American Studies Program's preservation of Ojibwe language and culture" xlink:href="/bitstream/handle/2027.42/93229/OOTB_302_PBS_build.mov?sequence=1&amp;isAllowed=y" xlink:type="locator" xlink:title="OOTB_302_PBS_build.mov"/>
</mets:file>
</mets:fileGrp>
</mets:fileSec>
<mets:structMap LABEL="DSpace" TYPE="LOGICAL">
<mets:div DMDID="dmd_1" TYPE="DSpace Item">
<mets:div ID="div_2" TYPE="DSpace Content Bitstream">
<mets:fptr FILEID="file_323082"/>
</mets:div>
</mets:div>
</mets:structMap>
</mets:METS>