<mets:METS xmlns:mets="http://www.loc.gov/METS/" xmlns:xlink="http://www.w3.org/TR/xlink/" xmlns:xsi="http://www.w3.org/2001/XMLSchema-instance" xmlns:dim="http://www.dspace.org/xmlns/dspace/dim" PROFILE="DSPACE METS SIP Profile 1.0" LABEL="DSpace Item" OBJID="/handle/2027.42/93496" ID="hdl:2027.42/93496" OBJEDIT="/admin/item?itemID=94837">
<mets:dmdSec GROUPID="group_dmd_0" ID="dmd_1">
<mets:mdWrap OTHERMDTYPE="DIM" MDTYPE="OTHER">
<mets:xmlData>
<dim:dim dspaceType="ITEM">
<dim:field qualifier="author" mdschema="dc" language="en_US" element="contributor">News and Information Services, University of Michigan</dim:field>
<dim:field qualifier="other" mdschema="dc" language="en_US" element="contributor">Moore, Nicole Casal</dim:field>
<dim:field qualifier="other" mdschema="dc" language="en_US" element="contributor">Zurbuchen, Thomas</dim:field>
<dim:field qualifier="temporal" mdschema="dc" language="en_US" element="coverage">2009</dim:field>
<dim:field qualifier="accessioned" mdschema="dc" element="date">2012-08-30T21:12:20Z</dim:field>
<dim:field qualifier="available" mdschema="dc" element="date">2012-08-30T21:12:20Z</dim:field>
<dim:field qualifier="created" mdschema="dc" language="en_US" element="date">2011</dim:field>
<dim:field qualifier="issued" mdschema="dc" language="en_US" element="date">2009</dim:field>
<dim:field qualifier="other" mdschema="dc" language="en_US" element="identifier">87265_0002</dim:field>
<dim:field qualifier="uri" mdschema="dc" element="identifier">http://hdl.handle.net/2027.42/93496</dim:field>
<dim:field qualifier="abstract" mdschema="dc" language="en_US" element="description">Neurophysiology for high school students. Crowdsourcing for product development. Socially-conscious t-shirts. These are three student business ideas getting started in Ann Arbor with help from the University of Michigan's Center for Entrepreneurship. The Center for Entrepreneurship helps student businesses Interviews with Thomas Zurbuchen, director of the Center for Entrepreneurship, plus interviews with founders of three student businesses: Crowd Clarity, Backyard Brains and The Bearon.</dim:field>
<dim:field qualifier="extent" mdschema="dc" language="en_US" element="format">0:04:39</dim:field>
<dim:field mdschema="dc" language="en_US" element="rights">Copyright is held by the Regents of the University of Michigan</dim:field>
<dim:field mdschema="dc" language="en_US" element="title">Student entrepreneurs</dim:field>
<dim:field mdschema="dc" language="en_US" element="type">Video</dim:field>
<dim:field qualifier="bitstreamurl" mdschema="dc" element="description">http://deepblue.lib.umich.edu/bitstream/2027.42/93496/1/studentbusiness_jun_09.mov</dim:field>
<dim:field qualifier="access" mdschema="dc" language="en_US" element="rights">The collection is open for research</dim:field>
<dim:field mdschema="dc" element="owningcollname">News and Information Services (University of Michigan) Sound and Video Recordings</dim:field>
</dim:dim>
</mets:xmlData>
</mets:mdWrap>
</mets:dmdSec>
<mets:fileSec>
<mets:fileGrp USE="CONTENT">
<mets:file GROUPID="group_file_323616" CHECKSUM="cb139548408e8c96c64148d5e37e1b8f" MIMETYPE="video/quicktime" SIZE="244690084" ID="file_323616" CHECKSUMTYPE="MD5">
<mets:FLocat LOCTYPE="URL" xlink:href="/bitstream/handle/2027.42/93496/studentbusiness_jun_09.mov?sequence=1&amp;isAllowed=y" xlink:type="locator" xlink:title="studentbusiness_jun_09.mov"/>
</mets:file>
</mets:fileGrp>
</mets:fileSec>
<mets:structMap LABEL="DSpace" TYPE="LOGICAL">
<mets:div DMDID="dmd_1" TYPE="DSpace Item">
<mets:div ID="div_2" TYPE="DSpace Content Bitstream">
<mets:fptr FILEID="file_323616"/>
</mets:div>
</mets:div>
</mets:structMap>
</mets:METS>